{
  "name": "aaa",
  "type": "package",
  "source": {
    "https": null,
    "ssh": null,
    "branch": "block_aaa"
  },
  "dependencies": {
    "addTodo": {
      "directory": "addTodo"
    },
    "listTodos": {
      "directory": "listTodos"
    },
    "removeTodo": {
      "directory": "removeTodo"
    },
    "todoItem": {
      "directory": "todoItem"
    },
    "todoInput": {
      "directory": "todoInput"
    },
    "todoContainer": {
      "directory": "todoContainer"
    }
  },
  "blockId": "8QpHA71yqLnXIA9rg_5uw",
  "parentBlockIDs": [],
  "isPublic": true,
  "supportedAppblockVersions": [
    "1.0.0"
  ],
  "repoType": "mono"
}